vectorlib/__init__.py
vectorlib_py-1.0.2.dist-info/LICENSE
vectorlib_py-1.0.2.dist-info/METADATA
vectorlib_py-1.0.2.dist-info/WHEEL
vectorlib_py-1.0.2.dist-info/top_level.txt
vectorlib_py-1.0.2.dist-info/RECORD
