Metadata-Version: 2.1
Name: vectorlib-py
Version: 1.0.2
Summary: A library to create and manage vectors in Python.
Author-email: Aarav Malani <aarav.malani@gmail.com>
Project-URL: Homepage, https://github.com/AaravMalani/vectorlib
Project-URL: Bug Tracker, https://github.com/AaravMalani/vectorlib/issues
Classifier: Programming Language :: Python :: 3
Classifier: License :: OSI Approved :: MIT License
Classifier: Operating System :: OS Independent
Requires-Python: >=3.6
License-File: LICENSE
